sixelcrop/__init__.py
sixelcrop/py.typed
sixelcrop-0.1.9.dist-info/METADATA
sixelcrop-0.1.9.dist-info/WHEEL
sixelcrop-0.1.9.dist-info/entry_points.txt
sixelcrop-0.1.9.dist-info/licenses/LICENSE.txt
sixelcrop-0.1.9.dist-info/RECORD
