Metadata-Version: 2.3
Name: sixelcrop
Version: 0.1.9
Summary: A library for cropping sixel images
Project-URL: Documentation, https://github.com/joouha/sixelcrop#readme
Project-URL: Issues, https://github.com/joouha/sixelcrop/issues
Project-URL: Source, https://github.com/joouha/sixelcrop
Author-email: Josiah Outram Halstead <josiah@halstead.email>
License-Expression: MIT
License-File: LICENSE.txt
Classifier: Development Status :: 4 - Beta
Classifier: Programming Language :: Python
Classifier: Programming Language :: Python :: 3.7
Classifier: Programming Language :: Python :: 3.8
Classifier: Programming Language :: Python :: 3.9
Classifier: Programming Language :: Python :: 3.10
Classifier: Programming Language :: Python :: 3.11
Classifier: Programming Language :: Python :: 3.12
Classifier: Programming Language :: Python :: Implementation :: CPython
Classifier: Programming Language :: Python :: Implementation :: PyPy
Requires-Python: >=3.7
